vmware_esxi/__init__.py
vmware_esxi/server.py
mcp_vmware_esxi-0.1.0.dist-info/METADATA
mcp_vmware_esxi-0.1.0.dist-info/WHEEL
mcp_vmware_esxi-0.1.0.dist-info/entry_points.txt
mcp_vmware_esxi-0.1.0.dist-info/licenses/LICENSE
mcp_vmware_esxi-0.1.0.dist-info/RECORD
