Metadata-Version: 2.4
Name: mcp-vmware-esxi
Version: 0.1.0
Summary: MCP server providing VMware vSphere/ESXi virtual machine management capabilities
Author: lohik
Maintainer: lohik
License: MIT License
License-File: LICENSE
Keywords: esxi,mcp,model-context-protocol,virtualization,vmware,vsphere
Classifier: Development Status :: 3 - Alpha
Classifier: Intended Audience :: Developers
Classifier: License :: OSI Approved :: MIT License
Classifier: Programming Language :: Python :: 3
Classifier: Programming Language :: Python :: 3.12
Classifier: Topic :: System :: Systems Administration
Requires-Python: >=3.12
Requires-Dist: mcp~=1.19.0
Requires-Dist: pyvmomi
Requires-Dist: pyyaml
Requires-Dist: uvicorn
Provides-Extra: dev
Requires-Dist: mypy~=1.8.0; extra == 'dev'
Requires-Dist: pytest-asyncio~=0.23.0; extra == 'dev'
Requires-Dist: pytest-cov~=4.1.0; extra == 'dev'
Requires-Dist: pytest-timeout~=2.2.0; extra == 'dev'
Requires-Dist: pytest~=8.0.0; extra == 'dev'
Requires-Dist: ruff~=0.1.0; extra == 'dev'
